tiny_gnupg/__init__.py
tiny_gnupg/tiny_gnupg.py
tiny_gnupg/gpghome/gpg2.conf
tiny_gnupg-0.9.0.dist-info/LICENSE
tiny_gnupg-0.9.0.dist-info/METADATA
tiny_gnupg-0.9.0.dist-info/WHEEL
tiny_gnupg-0.9.0.dist-info/top_level.txt
tiny_gnupg-0.9.0.dist-info/RECORD
