Metadata-Version: 2.1
Name: tiny-gnupg
Version: 0.9.0
Summary: tiny_gnupg - A small-as-possible solution for handling GnuPG ed25519 ECC keys.
Home-page: UNKNOWN
Author: Gonzo Investigative Journalism Agency, LLC
Author-email: gonzo.development@protonmail.ch
Maintainer: Gonzo Investigative Journalism Agency, LLC
Maintainer-email: gonzo.development@protonmail.ch
License: GPLv3
Download-URL: https://pypi.org/project/tiny-gnupg/
Project-URL: Source, https://github.com/rmlibre/tiny_gnupg
Project-URL: Tracker, https://github.com/rmlibre/tiny_gnupg/issues
Project-URL: Changelog, https://github.com/rmlibre/tiny_gnupg/blob/master/CHANGES.rst
Project-URL: Documentation, https://github.com/rmlibre/tiny_gnupg/blob/master/README.rst
Keywords: gpg gpg2 gnupg gnupg2 pgp openpgp org await async asyncio aiohttp clean simple code elliptic curve crypto ed25519 25519 wrapper automation adapter-pattern tor anonymous anonymity security appsec opsec infosec beta testing communications comms message messages encrypt encryption authentication decrypt decryption verify verification signature signatures SOCKSv5 socks5 proxy web key keys keyserver
Platform: UNKNOWN
Classifier: Framework :: AsyncIO
Classifier: Natural Language :: English
Classifier: Development Status :: 4 - Beta
Classifier: Topic :: Internet
Classifier: Topic :: Utilities
Classifier: Topic :: Internet :: WWW/HTTP
Classifier: Topic :: System :: Networking
Classifier: Topic :: Adaptive Technologies
Classifier: Topic :: Communications
Classifier: Topic :: Communications :: Email
Classifier: Topic :: Security :: Cryptography
Classifier: Operating System :: POSIX :: Linux
Classifier: Programming Language :: Python :: 3.6
Classifier: Intended Audience :: Developers
Classifier: Intended Audience :: Information Technology
Classifier: License :: OSI Approved :: GNU General Public License v3 (GPLv3)
Requires-Dist: aiohttp
Requires-Dist: aiohttp-socks
Requires-Dist: asyncio-contextmanager
